webscraper/__init__.py
webscraper/setup.py
webscraper/providers/__init__.py
webscraper/providers/bellikids/__init__.py
webscraper/providers/bellikids/scraper.py
webscraper_once-0.2.6.dist-info/LICENSE
webscraper_once-0.2.6.dist-info/METADATA
webscraper_once-0.2.6.dist-info/WHEEL
webscraper_once-0.2.6.dist-info/top_level.txt
webscraper_once-0.2.6.dist-info/RECORD
